{"paging":{"pageIndex":1,"pageSize":500,"total":37},"baseComponent":{"id":"AXumn8ZHQSvfWGEmVD1B","key":"fga-eps-mds_2021.1-Cartografia-social-api-users","name":"2021.1-Cartografia-social-api-users","qualifier":"TRK","measures":[{"metric":"duplicated_lines_density","value":"0.0","bestValue":true},{"metric":"functions","value":"61"},{"metric":"security_rating","value":"1.0","bestValue":true},{"metric":"files","value":"23"},{"metric":"complexity","value":"66"},{"metric":"ncloc","value":"601"},{"metric":"reliability_rating","value":"1.0","bestValue":true},{"metric":"comment_lines_density","value":"0.8","bestValue":false}]},"components":[{"id":"AXumoDUlMJij8kXIcZof","key":"fga-eps-mds_2021.1-Cartografia-social-api-users:test/app.e2e-spec.ts","name":"app.e2e-spec.ts","qualifier":"FIL","path":"test/app.e2e-spec.ts","language":"ts","measures":[{"metric":"complexity","value":"3"},{"metric":"functions","value":"3"},{"metric":"ncloc","value":"20"},{"metric":"reliability_rating","value":"1.0","bestValue":true},{"metric":"security_rating","value":"1.0","bestValue":true},{"metric":"comment_lines_density","value":"0.0","bestValue":false},{"metric":"files","value":"1"},{"metric":"duplicated_lines_density","value":"0.0","bestValue":true},{"metric":"test_success_density","value":"100.0","bestValue":true}]},{"id":"AXumoDUmMJij8kXIcZow","key":"fga-eps-mds_2021.1-Cartografia-social-api-users:src/app.module.ts","name":"app.module.ts","qualifier":"FIL","path":"src/app.module.ts","language":"ts","measures":[{"metric":"complexity","value":"0"},{"metric":"functions","value":"0"},{"metric":"ncloc","value":"17"},{"metric":"reliability_rating","value":"1.0","bestValue":true},{"metric":"security_rating","value":"1.0","bestValue":true},{"metric":"comment_lines_density","value":"0.0","bestValue":false},{"metric":"files","value":"1"},{"metric":"duplicated_lines_density","value":"0.0","bestValue":true},{"metric":"test_success_density","value":"100.0","bestValue":true}]},{"id":"AXvcIaaRh3CDW4xutViZ","key":"fga-eps-mds_2021.1-Cartografia-social-api-users:src/commons/auth","name":"auth","qualifier":"DIR","path":"src/commons/auth","measures":[{"metric":"duplicated_lines_density","value":"0.0","bestValue":true},{"metric":"functions","value":"5"},{"metric":"security_rating","value":"1.0","bestValue":true},{"metric":"files","value":"1"},{"metric":"complexity","value":"6"},{"metric":"ncloc","value":"34"},{"metric":"reliability_rating","value":"1.0","bestValue":true},{"metric":"comment_lines_density","value":"10.5","bestValue":false}]},{"id":"AXvcIaaRh3CDW4xutVia","key":"fga-eps-mds_2021.1-Cartografia-social-api-users:src/commons","name":"commons","qualifier":"DIR","path":"src/commons","measures":[{"metric":"duplicated_lines_density","value":"0.0","bestValue":true},{"metric":"functions","value":"6"},{"metric":"security_rating","value":"1.0","bestValue":true},{"metric":"files","value":"2"},{"metric":"complexity","value":"7"},{"metric":"ncloc","value":"44"},{"metric":"reliability_rating","value":"1.0","bestValue":true},{"metric":"comment_lines_density","value":"8.3","bestValue":false}]},{"id":"AXvcIaaRh3CDW4xutViV","key":"fga-eps-mds_2021.1-Cartografia-social-api-users:test/commons/auth","name":"commons/auth","qualifier":"DIR","path":"test/commons/auth","measures":[{"metric":"duplicated_lines_density","value":"0.0","bestValue":true},{"metric":"functions","value":"14"},{"metric":"security_rating","value":"1.0","bestValue":true},{"metric":"files","value":"1"},{"metric":"complexity","value":"14"},{"metric":"ncloc","value":"108"},{"metric":"reliability_rating","value":"1.0","bestValue":true},{"metric":"comment_lines_density","value":"0.9","bestValue":false}]},{"id":"AXumoDUmMJij8kXIcZoy","key":"fga-eps-mds_2021.1-Cartografia-social-api-users:src/config","name":"config","qualifier":"DIR","path":"src/config","measures":[{"metric":"duplicated_lines_density","value":"0.0","bestValue":true},{"metric":"functions","value":"2"},{"metric":"security_rating","value":"1.0","bestValue":true},{"metric":"files","value":"1"},{"metric":"complexity","value":"3"},{"metric":"ncloc","value":"32"},{"metric":"reliability_rating","value":"1.0","bestValue":true},{"metric":"comment_lines_density","value":"0.0","bestValue":false}]},{"id":"AXumoDUmMJij8kXIcZox","key":"fga-eps-mds_2021.1-Cartografia-social-api-users:src/config/configuration.ts","name":"configuration.ts","qualifier":"FIL","path":"src/config/configuration.ts","language":"ts","measures":[{"metric":"complexity","value":"3"},{"metric":"functions","value":"2"},{"metric":"ncloc","value":"32"},{"metric":"reliability_rating","value":"1.0","bestValue":true},{"metric":"security_rating","value":"1.0","bestValue":true},{"metric":"comment_lines_density","value":"0.0","bestValue":false},{"metric":"files","value":"1"},{"metric":"duplicated_lines_density","value":"0.0","bestValue":true},{"metric":"test_success_density","value":"100.0","bestValue":true}]},{"id":"AXumoDUmMJij8kXIcZop","key":"fga-eps-mds_2021.1-Cartografia-social-api-users:src/users/dto/create-user.dto.ts","name":"create-user.dto.ts","qualifier":"FIL","path":"src/users/dto/create-user.dto.ts","language":"ts","measures":[{"metric":"complexity","value":"0"},{"metric":"functions","value":"0"},{"metric":"ncloc","value":"6"},{"metric":"reliability_rating","value":"1.0","bestValue":true},{"metric":"security_rating","value":"1.0","bestValue":true},{"metric":"comment_lines_density","value":"0.0","bestValue":false},{"metric":"files","value":"1"},{"metric":"duplicated_lines_density","value":"0.0","bestValue":true},{"metric":"test_success_density","value":"100.0","bestValue":true}]},{"id":"AXu3neyaFLOs0JNfy2Yv","key":"fga-eps-mds_2021.1-Cartografia-social-api-users:deploy","name":"deploy","qualifier":"DIR","path":"deploy","measures":[{"metric":"duplicated_lines_density","value":"0.0","bestValue":true},{"metric":"security_rating","value":"1.0","bestValue":true},{"metric":"files","value":"2"},{"metric":"reliability_rating","value":"1.0","bestValue":true}]},{"id":"AXumoDUmMJij8kXIcZo0","key":"fga-eps-mds_2021.1-Cartografia-social-api-users:docker-compose.yml","name":"docker-compose.yml","qualifier":"FIL","path":"docker-compose.yml","language":"yaml","measures":[{"metric":"reliability_rating","value":"1.0","bestValue":true},{"metric":"security_rating","value":"1.0","bestValue":true},{"metric":"files","value":"1"},{"metric":"duplicated_lines_density","value":"0.0","bestValue":true},{"metric":"test_success_density","value":"100.0","bestValue":true}]},{"id":"AXu3neyaFLOs0JNfy2Yr","key":"fga-eps-mds_2021.1-Cartografia-social-api-users:deploy/hom/docker-compose.yml","name":"docker-compose.yml","qualifier":"FIL","path":"deploy/hom/docker-compose.yml","language":"yaml","measures":[{"metric":"reliability_rating","value":"1.0","bestValue":true},{"metric":"security_rating","value":"1.0","bestValue":true},{"metric":"files","value":"1"},{"metric":"duplicated_lines_density","value":"0.0","bestValue":true},{"metric":"test_success_density","value":"100.0","bestValue":true}]},{"id":"AXu3neyaFLOs0JNfy2Yt","key":"fga-eps-mds_2021.1-Cartografia-social-api-users:deploy/prod/docker-compose.yml","name":"docker-compose.yml","qualifier":"FIL","path":"deploy/prod/docker-compose.yml","language":"yaml","measures":[{"metric":"reliability_rating","value":"1.0","bestValue":true},{"metric":"security_rating","value":"1.0","bestValue":true},{"metric":"files","value":"1"},{"metric":"duplicated_lines_density","value":"0.0","bestValue":true},{"metric":"test_success_density","value":"100.0","bestValue":true}]},{"id":"AXumoDUmMJij8kXIcZor","key":"fga-eps-mds_2021.1-Cartografia-social-api-users:src/users/dto","name":"dto","qualifier":"DIR","path":"src/users/dto","measures":[{"metric":"duplicated_lines_density","value":"0.0","bestValue":true},{"metric":"functions","value":"0"},{"metric":"security_rating","value":"1.0","bestValue":true},{"metric":"files","value":"1"},{"metric":"complexity","value":"0"},{"metric":"ncloc","value":"6"},{"metric":"reliability_rating","value":"1.0","bestValue":true},{"metric":"comment_lines_density","value":"0.0","bestValue":false}]},{"id":"AXumoDUmMJij8kXIcZoo","key":"fga-eps-mds_2021.1-Cartografia-social-api-users:src/users/entities","name":"entities","qualifier":"DIR","path":"src/users/entities","measures":[{"metric":"duplicated_lines_density","value":"0.0","bestValue":true},{"metric":"functions","value":"2"},{"metric":"security_rating","value":"1.0","bestValue":true},{"metric":"files","value":"1"},{"metric":"complexity","value":"2"},{"metric":"ncloc","value":"35"},{"metric":"reliability_rating","value":"1.0","bestValue":true},{"metric":"comment_lines_density","value":"0.0","bestValue":false}]},{"id":"AXvcIaaRh3CDW4xutViX","key":"fga-eps-mds_2021.1-Cartografia-social-api-users:src/commons/exceptions","name":"exceptions","qualifier":"DIR","path":"src/commons/exceptions","measures":[{"metric":"duplicated_lines_density","value":"0.0","bestValue":true},{"metric":"functions","value":"1"},{"metric":"security_rating","value":"1.0","bestValue":true},{"metric":"files","value":"1"},{"metric":"complexity","value":"1"},{"metric":"ncloc","value":"10"},{"metric":"reliability_rating","value":"1.0","bestValue":true},{"metric":"comment_lines_density","value":"0.0","bestValue":false}]},{"id":"AXvcIaaRh3CDW4xutViU","key":"fga-eps-mds_2021.1-Cartografia-social-api-users:test/commons/auth/firebase.spec.ts","name":"firebase.spec.ts","qualifier":"FIL","path":"test/commons/auth/firebase.spec.ts","language":"ts","measures":[{"metric":"complexity","value":"14"},{"metric":"functions","value":"14"},{"metric":"ncloc","value":"108"},{"metric":"reliability_rating","value":"1.0","bestValue":true},{"metric":"security_rating","value":"1.0","bestValue":true},{"metric":"comment_lines_density","value":"0.9","bestValue":false},{"metric":"files","value":"1"},{"metric":"duplicated_lines_density","value":"0.0","bestValue":true},{"metric":"test_success_density","value":"100.0","bestValue":true}]},{"id":"AXvcIaaRh3CDW4xutViY","key":"fga-eps-mds_2021.1-Cartografia-social-api-users:src/commons/auth/firebase.ts","name":"firebase.ts","qualifier":"FIL","path":"src/commons/auth/firebase.ts","language":"ts","measures":[{"metric":"complexity","value":"6"},{"metric":"functions","value":"5"},{"metric":"ncloc","value":"34"},{"metric":"reliability_rating","value":"1.0","bestValue":true},{"metric":"security_rating","value":"1.0","bestValue":true},{"metric":"comment_lines_density","value":"10.5","bestValue":false},{"metric":"files","value":"1"},{"metric":"duplicated_lines_density","value":"0.0","bestValue":true},{"metric":"test_success_density","value":"100.0","bestValue":true}]},{"id":"AXu3neyaFLOs0JNfy2Ys","key":"fga-eps-mds_2021.1-Cartografia-social-api-users:deploy/hom","name":"hom","qualifier":"DIR","path":"deploy/hom","measures":[{"metric":"duplicated_lines_density","value":"0.0","bestValue":true},{"metric":"security_rating","value":"1.0","bestValue":true},{"metric":"files","value":"1"},{"metric":"reliability_rating","value":"1.0","bestValue":true}]},{"id":"AXumoDUlMJij8kXIcZoj","key":"fga-eps-mds_2021.1-Cartografia-social-api-users:test/jest-e2e.json","name":"jest-e2e.json","qualifier":"FIL","path":"test/jest-e2e.json","language":"json","measures":[{"metric":"reliability_rating","value":"1.0","bestValue":true},{"metric":"security_rating","value":"1.0","bestValue":true},{"metric":"files","value":"1"},{"metric":"duplicated_lines_density","value":"0.0","bestValue":true},{"metric":"test_success_density","value":"100.0","bestValue":true}]},{"id":"AXumoDUmMJij8kXIcZov","key":"fga-eps-mds_2021.1-Cartografia-social-api-users:src/main.ts","name":"main.ts","qualifier":"FIL","path":"src/main.ts","language":"ts","measures":[{"metric":"complexity","value":"1"},{"metric":"functions","value":"1"},{"metric":"ncloc","value":"28"},{"metric":"reliability_rating","value":"1.0","bestValue":true},{"metric":"security_rating","value":"1.0","bestValue":true},{"metric":"comment_lines_density","value":"0.0","bestValue":false},{"metric":"files","value":"1"},{"metric":"duplicated_lines_density","value":"0.0","bestValue":true},{"metric":"test_success_density","value":"100.0","bestValue":true}]},{"id":"AXvcIaaRh3CDW4xutViW","key":"fga-eps-mds_2021.1-Cartografia-social-api-users:src/commons/exceptions/MicrosserviceException.ts","name":"MicrosserviceException.ts","qualifier":"FIL","path":"src/commons/exceptions/MicrosserviceException.ts","language":"ts","measures":[{"metric":"complexity","value":"1"},{"metric":"functions","value":"1"},{"metric":"ncloc","value":"10"},{"metric":"reliability_rating","value":"1.0","bestValue":true},{"metric":"security_rating","value":"1.0","bestValue":true},{"metric":"comment_lines_density","value":"0.0","bestValue":false},{"metric":"files","value":"1"},{"metric":"duplicated_lines_density","value":"0.0","bestValue":true},{"metric":"test_success_density","value":"100.0","bestValue":true}]},{"id":"AXumoDUlMJij8kXIcZoe","key":"fga-eps-mds_2021.1-Cartografia-social-api-users:nest-cli.json","name":"nest-cli.json","qualifier":"FIL","path":"nest-cli.json","language":"json","measures":[{"metric":"reliability_rating","value":"1.0","bestValue":true},{"metric":"security_rating","value":"1.0","bestValue":true},{"metric":"files","value":"1"},{"metric":"duplicated_lines_density","value":"0.0","bestValue":true},{"metric":"test_success_density","value":"100.0","bestValue":true}]},{"id":"AXumoDUmMJij8kXIcZol","key":"fga-eps-mds_2021.1-Cartografia-social-api-users:package-lock.json","name":"package-lock.json","qualifier":"FIL","path":"package-lock.json","language":"json","measures":[{"metric":"reliability_rating","value":"1.0","bestValue":true},{"metric":"security_rating","value":"1.0","bestValue":true},{"metric":"files","value":"1"},{"metric":"duplicated_lines_density","value":"0.0","bestValue":true},{"metric":"test_success_density","value":"100.0","bestValue":true}]},{"id":"AXumoDUmMJij8kXIcZo3","key":"fga-eps-mds_2021.1-Cartografia-social-api-users:package.json","name":"package.json","qualifier":"FIL","path":"package.json","language":"json","measures":[{"metric":"reliability_rating","value":"1.0","bestValue":true},{"metric":"security_rating","value":"1.0","bestValue":true},{"metric":"files","value":"1"},{"metric":"duplicated_lines_density","value":"0.0","bestValue":true},{"metric":"test_success_density","value":"100.0","bestValue":true}]},{"id":"AXu3neyaFLOs0JNfy2Yu","key":"fga-eps-mds_2021.1-Cartografia-social-api-users:deploy/prod","name":"prod","qualifier":"DIR","path":"deploy/prod","measures":[{"metric":"duplicated_lines_density","value":"0.0","bestValue":true},{"metric":"security_rating","value":"1.0","bestValue":true},{"metric":"files","value":"1"},{"metric":"reliability_rating","value":"1.0","bestValue":true}]},{"id":"AXumoDUmMJij8kXIcZoz","key":"fga-eps-mds_2021.1-Cartografia-social-api-users:src","name":"src","qualifier":"DIR","path":"src","measures":[{"metric":"duplicated_lines_density","value":"0.0","bestValue":true},{"metric":"functions","value":"18"},{"metric":"security_rating","value":"1.0","bestValue":true},{"metric":"files","value":"10"},{"metric":"complexity","value":"23"},{"metric":"ncloc","value":"269"},{"metric":"reliability_rating","value":"1.0","bestValue":true},{"metric":"comment_lines_density","value":"1.5","bestValue":false}]},{"id":"AXumoDUmMJij8kXIcZok","key":"fga-eps-mds_2021.1-Cartografia-social-api-users:test","name":"test","qualifier":"DIR","path":"test","measures":[{"metric":"duplicated_lines_density","value":"0.0","bestValue":true},{"metric":"functions","value":"43"},{"metric":"security_rating","value":"1.0","bestValue":true},{"metric":"files","value":"5"},{"metric":"complexity","value":"43"},{"metric":"ncloc","value":"332"},{"metric":"reliability_rating","value":"1.0","bestValue":true},{"metric":"comment_lines_density","value":"0.3","bestValue":false}]},{"id":"AXumoDUmMJij8kXIcZo1","key":"fga-eps-mds_2021.1-Cartografia-social-api-users:tsconfig.build.json","name":"tsconfig.build.json","qualifier":"FIL","path":"tsconfig.build.json","language":"json","measures":[{"metric":"reliability_rating","value":"1.0","bestValue":true},{"metric":"security_rating","value":"1.0","bestValue":true},{"metric":"files","value":"1"},{"metric":"duplicated_lines_density","value":"0.0","bestValue":true},{"metric":"test_success_density","value":"100.0","bestValue":true}]},{"id":"AXumoDUmMJij8kXIcZo2","key":"fga-eps-mds_2021.1-Cartografia-social-api-users:tsconfig.json","name":"tsconfig.json","qualifier":"FIL","path":"tsconfig.json","language":"json","measures":[{"metric":"reliability_rating","value":"1.0","bestValue":true},{"metric":"security_rating","value":"1.0","bestValue":true},{"metric":"files","value":"1"},{"metric":"duplicated_lines_density","value":"0.0","bestValue":true},{"metric":"test_success_density","value":"100.0","bestValue":true}]},{"id":"AXumoDUmMJij8kXIcZon","key":"fga-eps-mds_2021.1-Cartografia-social-api-users:src/users/entities/user.entity.ts","name":"user.entity.ts","qualifier":"FIL","path":"src/users/entities/user.entity.ts","language":"ts","measures":[{"metric":"complexity","value":"2"},{"metric":"functions","value":"2"},{"metric":"ncloc","value":"35"},{"metric":"reliability_rating","value":"1.0","bestValue":true},{"metric":"security_rating","value":"1.0","bestValue":true},{"metric":"comment_lines_density","value":"0.0","bestValue":false},{"metric":"files","value":"1"},{"metric":"duplicated_lines_density","value":"0.0","bestValue":true},{"metric":"test_success_density","value":"100.0","bestValue":true}]},{"id":"AXumoDUlMJij8kXIcZoi","key":"fga-eps-mds_2021.1-Cartografia-social-api-users:test/users","name":"users","qualifier":"DIR","path":"test/users","measures":[{"metric":"duplicated_lines_density","value":"0.0","bestValue":true},{"metric":"functions","value":"26"},{"metric":"security_rating","value":"1.0","bestValue":true},{"metric":"files","value":"2"},{"metric":"complexity","value":"26"},{"metric":"ncloc","value":"204"},{"metric":"reliability_rating","value":"1.0","bestValue":true},{"metric":"comment_lines_density","value":"0.0","bestValue":false}]},{"id":"AXumoDUmMJij8kXIcZou","key":"fga-eps-mds_2021.1-Cartografia-social-api-users:src/users","name":"users","qualifier":"DIR","path":"src/users","measures":[{"metric":"duplicated_lines_density","value":"0.0","bestValue":true},{"metric":"functions","value":"9"},{"metric":"security_rating","value":"1.0","bestValue":true},{"metric":"files","value":"5"},{"metric":"complexity","value":"12"},{"metric":"ncloc","value":"148"},{"metric":"reliability_rating","value":"1.0","bestValue":true},{"metric":"comment_lines_density","value":"0.0","bestValue":false}]},{"id":"AXumoDUlMJij8kXIcZog","key":"fga-eps-mds_2021.1-Cartografia-social-api-users:test/users/users.controller.spec.ts","name":"users.controller.spec.ts","qualifier":"FIL","path":"test/users/users.controller.spec.ts","language":"ts","measures":[{"metric":"complexity","value":"12"},{"metric":"functions","value":"12"},{"metric":"ncloc","value":"90"},{"metric":"reliability_rating","value":"1.0","bestValue":true},{"metric":"security_rating","value":"1.0","bestValue":true},{"metric":"comment_lines_density","value":"0.0","bestValue":false},{"metric":"files","value":"1"},{"metric":"duplicated_lines_density","value":"0.0","bestValue":true},{"metric":"test_success_density","value":"100.0","bestValue":true}]},{"id":"AXumoDUmMJij8kXIcZot","key":"fga-eps-mds_2021.1-Cartografia-social-api-users:src/users/users.controller.ts","name":"users.controller.ts","qualifier":"FIL","path":"src/users/users.controller.ts","language":"ts","measures":[{"metric":"complexity","value":"4"},{"metric":"functions","value":"4"},{"metric":"ncloc","value":"30"},{"metric":"reliability_rating","value":"1.0","bestValue":true},{"metric":"security_rating","value":"1.0","bestValue":true},{"metric":"comment_lines_density","value":"0.0","bestValue":false},{"metric":"files","value":"1"},{"metric":"duplicated_lines_density","value":"0.0","bestValue":true},{"metric":"test_success_density","value":"100.0","bestValue":true}]},{"id":"AXumoDUmMJij8kXIcZom","key":"fga-eps-mds_2021.1-Cartografia-social-api-users:src/users/users.module.ts","name":"users.module.ts","qualifier":"FIL","path":"src/users/users.module.ts","language":"ts","measures":[{"metric":"complexity","value":"0"},{"metric":"functions","value":"0"},{"metric":"ncloc","value":"22"},{"metric":"reliability_rating","value":"1.0","bestValue":true},{"metric":"security_rating","value":"1.0","bestValue":true},{"metric":"comment_lines_density","value":"0.0","bestValue":false},{"metric":"files","value":"1"},{"metric":"duplicated_lines_density","value":"0.0","bestValue":true},{"metric":"test_success_density","value":"100.0","bestValue":true}]},{"id":"AXumoDUlMJij8kXIcZoh","key":"fga-eps-mds_2021.1-Cartografia-social-api-users:test/users/users.service.spec.ts","name":"users.service.spec.ts","qualifier":"FIL","path":"test/users/users.service.spec.ts","language":"ts","measures":[{"metric":"complexity","value":"14"},{"metric":"functions","value":"14"},{"metric":"ncloc","value":"114"},{"metric":"reliability_rating","value":"1.0","bestValue":true},{"metric":"security_rating","value":"1.0","bestValue":true},{"metric":"comment_lines_density","value":"0.0","bestValue":false},{"metric":"files","value":"1"},{"metric":"duplicated_lines_density","value":"0.0","bestValue":true},{"metric":"test_success_density","value":"100.0","bestValue":true}]},{"id":"AXumoDUmMJij8kXIcZos","key":"fga-eps-mds_2021.1-Cartografia-social-api-users:src/users/users.service.ts","name":"users.service.ts","qualifier":"FIL","path":"src/users/users.service.ts","language":"ts","measures":[{"metric":"complexity","value":"6"},{"metric":"functions","value":"3"},{"metric":"ncloc","value":"55"},{"metric":"reliability_rating","value":"1.0","bestValue":true},{"metric":"security_rating","value":"1.0","bestValue":true},{"metric":"comment_lines_density","value":"0.0","bestValue":false},{"metric":"files","value":"1"},{"metric":"duplicated_lines_density","value":"0.0","bestValue":true},{"metric":"test_success_density","value":"100.0","bestValue":true}]}]}